bicam/__init__.py
bicam/__version__.py
bicam/_auth.py
bicam/cli.py
bicam/config.py
bicam/datasets.py
bicam/downloader.py
bicam/py.typed
bicam/utils.py
bicam-0.1.3.dist-info/licenses/LICENSE
bicam-0.1.3.dist-info/METADATA
bicam-0.1.3.dist-info/WHEEL
bicam-0.1.3.dist-info/entry_points.txt
bicam-0.1.3.dist-info/top_level.txt
bicam-0.1.3.dist-info/RECORD
