Metadata-Version: 2.4
Name: bicam
Version: 0.1.3
Summary: BICAM Dataset Downloader - Access comprehensive congressional data
Author-email: Ryan Delano <bicam.data@gmail.com>
Maintainer-email: Ryan Delano <bicam.data@gmail.com>
License: MIT
Project-URL: Homepage, https://github.com/bicam-data/bicam
Project-URL: Documentation, https://bicam.readthedocs.io
Project-URL: Repository, https://github.com/bicam-data/bicam.git
Project-URL: Issues, https://github.com/bicam-data/bicam/issues
Project-URL: Changelog, https://github.com/bicam-data/bicam/blob/main/CHANGELOG.md
Keywords: congress,legislation,political-science,dataset,government-data
Classifier: Development Status :: 4 - Beta
Classifier: Intended Audience :: Science/Research
Classifier: License :: OSI Approved :: MIT License
Classifier: Operating System :: OS Independent
Classifier: Programming Language :: Python :: 3
Classifier: Programming Language :: Python :: 3.8
Classifier: Programming Language :: Python :: 3.9
Classifier: Programming Language :: Python :: 3.10
Classifier: Programming Language :: Python :: 3.11
Classifier: Programming Language :: Python :: 3.12
Classifier: Topic :: Scientific/Engineering :: Information Analysis
Classifier: Topic :: Software Development :: Libraries :: Python Modules
Requires-Python: >=3.8
License-File: LICENSE
Requires-Dist: boto3>=1.26.0
Requires-Dist: tqdm>=4.65.0
Requires-Dist: pandas>=1.3.0
Requires-Dist: polars>=0.20.0
Requires-Dist: requests>=2.28.0
Requires-Dist: click>=8.0.0
Requires-Dist: python-dotenv>=1.0.0
Provides-Extra: dev
Requires-Dist: pytest>=8.3.5; extra == "dev"
Requires-Dist: pytest-cov>=5.0.0; extra == "dev"
Requires-Dist: pytest-mock>=3.10.0; extra == "dev"
Requires-Dist: black>=22.0.0; extra == "dev"
Requires-Dist: ruff>=0.1.0; extra == "dev"
Requires-Dist: mypy>=0.990; extra == "dev"
Requires-Dist: moto>=5.0.28; extra == "dev"
Requires-Dist: responses>=0.22.0; extra == "dev"
Requires-Dist: sphinx>=7.0.0; extra == "dev"
Requires-Dist: sphinx-rtd-theme>=1.3.0; extra == "dev"
Requires-Dist: sphinx-autodoc-typehints>=1.24.0; extra == "dev"
Dynamic: license-file
